专业基础/数字系统设计/作业/作业5verilog+边沿触发器/verilog代码答案/src/code/pr_encoder.v
//功能：优先编码器，4输入三输出。
module pr_encoder(
  input [3:0] D,
  output reg [1:0] out,
  output reg v
);
  always @(*) begin
    if( D == 4'b0000 ) begin
      out = 2'b00;
      v = 1'b0;
    end
    else if( D[3] == 1 ) begin
      out = 2'b11;
      v = 1'b1;
    end
    else if( D[2] == 1 ) begin
      out = 2'b10;
      v = 1'b1;
    end
    else if( D[1] == 1 ) begin
      out = 2'b01;
      v = 1'b1;
    end
    else if( D[0] == 1 ) begin
      out = 2'b00;
      v = 1'b1;
    end
    else begin
      out = 2'b00;
      v = 1'b0;
    end
  end
endmodule

专业基础/数字系统设计/作业/作业5verilog+边沿触发器/verilog代码答案/src/testbench/pr_encoder_tb.v
// 优先编码器测试平台
`timescale 1ns/1ps  // 时间单位/精度

module pr_encoder_tb();

  // 测试信号声明
  reg [3:0] in_tb;        // 测试输入
  wire [1:0] out_tb;      // 测试输出
  wire v_tb;              // 有效标志输出
  
  // 实例化被测试模块
  pr_encoder pr_encoder_instance (
    .D(in_tb),
    .out(out_tb),
    .v(v_tb)
  );
  
  // 测试过程
  initial begin
    // 显示测试开始信息
    $display("开始测试优先编码器");
    // 测试用例1：无输入
    in_tb = 4'b0000;
    #10;
    
    // 测试用例2：最高位优先
    in_tb = 4'b1000;  // in[3] = 1
    #10;
    
    in_tb = 4'b1100;  // 多个1，应输出in[3]的编码
    #10;
    
    // 测试用例3：次高位优先
    in_tb = 4'b0100;  // in[2] = 1
    #10;
    
    in_tb = 4'b0110;  // 应输出in[2]的编码
    #10;
    
    // 测试用例4：第三位优先
    in_tb = 4'b0010;  // in[1] = 1
    #10;
    
    in_tb = 4'b0011;  // 应输出in[1]的编码
    #10;
    
    // 测试用例5：最低位优先
    in_tb = 4'b0001;  // in[0] = 1
    #10;
    
    // 测试用例6：随机测试
    in_tb = 4'b1010;
    #10;
    
    in_tb = 4'b0101;
    #10;
    
    in_tb = 4'b1111;  // 全1，应输出in[3]的编码
    #10;
    
    // 测试结束
    #10;
    $display("========================================");
    $display("测试完成");
    $display("========================================");
    $finish();
  end
  
  // 生成波形文件（用于波形查看）
  initial begin
    $dumpfile("prj/vcd/pr_encoder_tb.vcd");  // 波形文件名
    $dumpvars(0, pr_encoder_tb);      // 记录所有变量
  end

endmodule

专业基础/数字系统设计/作业/作业5verilog+边沿触发器/verilog代码答案/prj/vcd/pr_encoder_tb.vcd
$date
	Mon Mar 30 20:58:26 2026
$end
$version
	Icarus Verilog
$end
$timescale
	1ps
$end
$scope module pr_encoder_tb $end
$var wire 1 ! v_tb $end
$var wire 2 " out_tb [1:0] $end
$var reg 4 # in_tb [3:0] $end
$scope module pr_encoder_instance $end
$var wire 4 $ D [3:0] $end
$var reg 2 % out [1:0] $end
$var reg 1 ! v $end
$upscope $end
$upscope $end
$enddefinitions $end
$comment Show the parameter values. $end
$dumpall
$end
#0
$dumpvars
b0 %
b0 $
b0 #
b0 "
0!
$end
#10000
1!
b11 "
b11 %
b1000 #
b1000 $
#20000
b1100 #
b1100 $
#30000
b10 "
b10 %
b100 #
b100 $
#40000
b110 #
b110 $
#50000
b1 "
b1 %
b10 #
b10 $
#60000
b11 #
b11 $
#70000
b0 "
b0 %
b1 #
b1 $
#80000
b11 "
b11 %
b1010 #
b1010 $
#90000
b10 "
b10 %
b101 #
b101 $
#100000
b11 "
b11 %
b1111 #
b1111 $
