专业基础/数字系统设计实验/实验完整代码lab1-3-5-11-15-19/lab11_button_process_unit/src/code/PWM/PWM.v
//脉宽变化电路
module PWM(
    input wire in,
    input wire clk,
    output wire out
);
    reg q;
    always @(posedge clk) begin
        q <= in;
    end
    assign out = (~q) & in;

endmodule

专业基础/数字系统设计实验/实验完整代码lab1-3-5-11-15-19/lab11_button_process_unit/src/code/debouncer/counter.v
module counter #(
    parameter n, //mod number
    parameter counter_bits  //number of bits needed to count to n
)(
    input clk,
    input reset,
    input en,
    output reg [counter_bits-1:0] q,
    output co
);
    assign co = (q == n-1) && en; //carry generates when q equals to n-1 and en signal is true
    always @(posedge clk) begin
        if (reset) q <= 0; //if reset is true, then reset q to 0
        else if (en) begin
            if (q == n-1) q <= 0; //if q equals to n-1, then reset q to 0
            else q <= q + 1;
        end
    end
endmodule

专业基础/数字系统设计实验/实验完整代码lab1-3-5-11-15-19/lab11_button_process_unit/src/code/debouncer/controller.v
module controller(
    input clk,
    inout reset,//异步复位
    input in,//按键输入
    input timer_done,//定时完成信号
    output timer_clr,//开始定时信号
    output reg out //调理后的按键输出信号
);
    reg state, next_state;
    parameter HIGH = 2'b00, LOW = 2'b01, WAIT_HIGH = 2'b10, WAIT_LOW = 2'b11;
    always @(*) begin
        case(state)
            HIGH: next_state = in ? HIGH : WAIT_LOW;
            LOW: next_state = in ? WAIT_HIGH : LOW;
            WAIT_HIGH: next_state = timer_done ? HIGH : WAIT_HIGH;
            WAIT_LOW: next_state = timer_done ? LOW : WAIT_LOW;
        endcase
    end
    always @(posedge clk or posedge reset) begin
        if (reset) state <= LOW;
        else state <= next_state;
    end
    assign timer_clr = (state == HIGH || state == LOW) ? 1 : 0;
    assign out = (state == LOW) ? 0 : 1;
endmodule

专业基础/数字系统设计实验/实验完整代码lab1-3-5-11-15-19/lab11_button_process_unit/src/code/debouncer/debouncer.v
module debouncer
    #(
        parameter  sim = 1
    )
    (
        input clk,
        input reset,//异步复位
        input in,//按键输入
        output out //调理后的按键输出信号
    );
wire timer_clr, timer_done, pluse1kHz;

counter #(
        .n(sim?32:100000), 
        .counter_bits(sim?5:17))
frency_division(
    .clk(clk),
    .reset(1'b0),
    .en(1'b1),
    .co(pluse1kHz),
    .q()
);

controller c0(
    .clk(clk),
    .reset(reset),
    .in(in),
    .timer_done(timer_done),
    .timer_clr(timer_clr),
    .out(out)
);

counter #(
    .n            	(10  ),
    .counter_bits 	(4  ))
timer(
    .clk   	(clk    ),
    .reset 	(timer_clr  ),
    .en    	(pluse1kHz     ),
    .q     	(      ),
    .co    	(timer_done     )
);


endmodule

专业基础/数字系统设计实验/实验完整代码lab1-3-5-11-15-19/lab11_button_process_unit/src/code/syncer/syncer.v
//同步器
module syncer(
    input asynch_in,
    input clk,
    output synch_out
);
    reg q1;
    reg q2;

    always @(posedge clk) begin
        q1 <= asynch_in;
        q2 <= q1;
    end

    assign synch_out = q2;
endmodule

专业基础/数字系统设计实验/实验完整代码lab1-3-5-11-15-19/lab11_button_process_unit/src/code/button_press_unit.v
module button_press_unit
    #(parameter sim = 1)
(
    input  clk,
    input  reset,
    input  button_in,
    output  button_out
);
    // output declaration of module syncer
    wire synch_out;
    
    syncer u_syncer(
        .asynch_in 	(button_in  ),
        .clk       	(clk        ),
        .synch_out 	(synch_out  )
    );
    
    // output declaration of module debouncer
    wire out;
    
    debouncer #(
        .sim(sim))
    u_debouncer(
        .clk   	(clk    ),
        .reset 	(reset  ),
        .in    	(synch_out     ),
        .out   	(out    )
    );
    
    // output declaration of module PWM
    
    PWM u_PWM(
        .in  	(out   ),
        .clk 	(clk  ),
        .out 	(button_out  )
    );
    
endmodule

专业基础/数字系统设计实验/实验完整代码lab1-3-5-11-15-19/lab11_button_process_unit/src/testbench/button_process_unit_tb.v
`timescale 1ns / 10ps

module button_press_tb;
  reg clk,ButtonIn,reset;
  wire ButtonOut;
  parameter delay=10;
//  
   initial begin
      clk = 0;	reset = 1;	ButtonIn = 0;
      #(delay*3+1) reset=0;
      #(delay*100 )   
       repeat (25) 
         begin
           #(delay*5) ButtonIn=0;
           #(delay*5) ButtonIn=1;
         end
       #(delay*900) 
         repeat (25)
            begin
            #(delay*5) ButtonIn=1;
            #(delay*5) ButtonIn=0;
          end
       #(delay*1200) 
          repeat (25) 
         begin
           #(delay*5) ButtonIn=0;
           #(delay*5) ButtonIn=1;
         end
       #(delay*900) 
         repeat (25)
            begin
            #(delay*5) ButtonIn=1;
            #(delay*5) ButtonIn=0;
          end
       #(delay*100) 
       $finish();;
      end
 //     
    always #(delay/2) clk=~clk;
 //

initial begin
  $dumpfile("prj/vcd/button_press_unit_tb.vcd");
  $dumpvars(0, button_press_tb);
end
button_press_unit #(.sim(1))  button_unit(
  .clk(clk),
  .reset(reset),
  .button_in(ButtonIn),
  .button_out(ButtonOut)
   );

endmodule

专业基础/数字系统设计实验/实验完整代码lab1-3-5-11-15-19/lab11_button_process_unit/prj/vcd/button_press_unit_tb.vcd
$date
	Mon Apr 13 20:49:36 2026
$end
$version
	Icarus Verilog
$end
$timescale
	10ps
$end
$scope module button_press_tb $end
$var wire 1 ! ButtonOut $end
$var parameter 32 " delay $end
$var reg 1 # ButtonIn $end
$var reg 1 $ clk $end
$var reg 1 % reset $end
$scope module button_unit $end
$var wire 1 # button_in $end
$var wire 1 $ clk $end
$var wire 1 % reset $end
$var wire 1 & synch_out $end
$var wire 1 ' out $end
$var wire 1 ! button_out $end
$var parameter 32 ( sim $end
$scope module u_PWM $end
$var wire 1 $ clk $end
$var wire 1 ! out $end
$var wire 1 ' in $end
$var reg 1 ) q $end
$upscope $end
$scope module u_debouncer $end
$var wire 1 $ clk $end
$var wire 1 % reset $end
$var wire 1 * timer_done $end
$var wire 1 + timer_clr $end
$var wire 1 , pluse1kHz $end
$var wire 1 ' out $end
$var wire 1 & in $end
$var parameter 32 - sim $end
$scope module c0 $end
$var wire 1 $ clk $end
$var wire 1 % reset $end
$var wire 1 * timer_done $end
$var wire 1 + timer_clr $end
$var wire 1 ' out $end
$var wire 1 & in $end
$var parameter 2 . HIGH $end
$var parameter 2 / LOW $end
$var parameter 2 0 WAIT_HIGH $end
$var parameter 2 1 WAIT_LOW $end
$var reg 1 2 next_state $end
$var reg 1 3 state $end
$upscope $end
$scope module frency_division $end
$var wire 1 $ clk $end
$var wire 1 , co $end
$var wire 1 4 en $end
$var wire 1 5 reset $end
$var parameter 32 6 counter_bits $end
$var parameter 32 7 n $end
$var reg 5 8 q [4:0] $end
$upscope $end
$scope module timer $end
$var wire 1 $ clk $end
$var wire 1 * co $end
$var wire 1 , en $end
$var wire 1 + reset $end
$var parameter 32 9 counter_bits $end
$var parameter 32 : n $end
$var reg 4 ; q [3:0] $end
$upscope $end
$upscope $end
$scope module u_syncer $end
$var wire 1 # asynch_in $end
$var wire 1 $ clk $end
$var wire 1 & synch_out $end
$var reg 1 < q1 $end
$var reg 1 = q2 $end
$upscope $end
$upscope $end
$upscope $end
$enddefinitions $end
$comment Show the parameter values. $end
$dumpall
b1010 :
b100 9
b100000 7
b101 6
b11 1
b10 0
b1 /
b0 .
b1 -
b1 (
b1010 "
$end
#0
$dumpvars
x=
x<
bx ;
bx 8
05
14
13
x2
x,
1+
x*
x)
0'
x&
1%
0$
0#
0!
$end
#500
0*
0<
b0 ;
0)
1$
#1000
0$
#1500
12
0&
0=
1$
#2000
0$
#2500
1$
#3000
0$
#3100
0%
#3500
1$
#4000
0$
#4500
1$
#5000
0$
#5500
1$
#6000
0$
#6500
1$
#7000
0$
#7500
1$
#8000
0$
#8500
1$
#9000
0$
#9500
1$
#10000
0$
#10500
1$
#11000
0$
#11500
1$
#12000
0$
#12500
1$
#13000
0$
#13500
1$
#14000
0$
#14500
1$
#15000
0$
#15500
1$
#16000
0$
#16500
1$
#17000
0$
#17500
1$
#18000
0$
#18500
1$
#19000
0$
#19500
1$
#20000
0$
#20500
1$
#21000
0$
#21500
1$
#22000
0$
#22500
1$
#23000
0$
#23500
1$
#24000
0$
#24500
1$
#25000
0$
#25500
1$
#26000
0$
#26500
1$
#27000
0$
#27500
1$
#28000
0$
#28500
1$
#29000
0$
#29500
1$
#30000
0$
#30500
1$
#31000
0$
#31500
1$
#32000
0$
#32500
1$
#33000
0$
#33500
1$
#34000
0$
#34500
1$
#35000
0$
#35500
1$
#36000
0$
#36500
1$
#37000
0$
#37500
1$
#38000
0$
#38500
1$
#39000
0$
#39500
1$
#40000
0$
#40500
1$
#41000
0$
#41500
1$
#42000
0$
#42500
1$
#43000
0$
#43500
1$
#44000
0$
#44500
1$
#45000
0$
#45500
1$
#46000
0$
#46500
1$
#47000
0$
#47500
1$
#48000
0$
#48500
1$
#49000
0$
#49500
1$
#50000
0$
#50500
1$
#51000
0$
#51500
1$
#52000
0$
#52500
1$
#53000
0$
#53500
1$
#54000
0$
#54500
1$
#55000
0$
#55500
1$
#56000
0$
#56500
1$
#57000
0$
#57500
1$
#58000
0$
#58500
1$
#59000
0$
#59500
1$
#60000
0$
#60500
1$
#61000
0$
#61500
1$
#62000
0$
#62500
1$
#63000
0$
#63500
1$
#64000
0$
#64500
1$
#65000
0$
#65500
1$
#66000
0$
#66500
1$
#67000
0$
#67500
1$
#68000
0$
#68500
1$
#69000
0$
#69500
1$
#70000
0$
#70500
1$
#71000
0$
#71500
1$
#72000
0$
#72500
1$
#73000
0$
#73500
1$
#74000
0$
#74500
1$
#75000
0$
#75500
1$
#76000
0$
#76500
1$
#77000
0$
#77500
1$
#78000
0$
#78500
1$
#79000
0$
#79500
1$
#80000
0$
#80500
1$
#81000
0$
#81500
1$
#82000
0$
#82500
1$
#83000
0$
#83500
1$
#84000
0$
#84500
1$
#85000
0$
#85500
1$
#86000
0$
#86500
1$
#87000
0$
#87500
1$
#88000
0$
#88500
1$
#89000
0$
#89500
1$
#90000
0$
#90500
1$
#91000
0$
#91500
1$
#92000
0$
#92500
1$
#93000
0$
#93500
1$
#94000
0$
#94500
1$
#95000
0$
#95500
1$
#96000
0$
#96500
1$
#97000
0$
#97500
1$
#98000
0$
#98500
1$
#99000
0$
#99500
1$
#100000
0$
#100500
1$
#101000
0$
#101500
1$
#102000
0$
#102500
1$
#103000
0$
#103500
1$
#104000
0$
#104500
1$
#105000
0$
#105500
1$
#106000
0$
#106500
1$
#107000
0$
#107500
1$
#108000
0$
#108500
1$
#109000
0$
#109500
1$
#110000
0$
#110500
1$
#111000
0$
#111500
1$
#112000
0$
#112500
1$
#113000
0$
#113100
1#
#113500
1<
1$
#114000
0$
#114500
02
1&
1=
1$
#115000
0$
#115500
1!
1'
03
1$
#116000
0$
#116500
0!
1)
1$
#117000
0$
#117500
1$
#118000
0$
#118100
0#
#118500
0<
1$
#119000
0$
#119500
12
0&
0=
1$
#120000
0$
#120500
0'
13
1$
#121000
0$
#121500
0)
1$
#122000
0$
#122500
1$
#123000
0$
#123100
1#
#123500
1<
1$
#124000
0$
#124500
02
1&
1=
1$
#125000
0$
#125500
1!
1'
03
1$
#126000
0$
#126500
0!
1)
1$
#127000
0$
#127500
1$
#128000
0$
#128100
0#
#128500
0<
1$
#129000
0$
#129500
12
0&
0=
1$
#130000
0$
#130500
0'
13
1$
#131000
0$
#131500
0)
1$
#132000
0$
#132500
1$
#133000
0$
#133100
1#
#133500
1<
1$
#134000
0$
#134500
02
1&
1=
1$
#135000
0$
#135500
1!
1'
03
1$
#136000
0$
#136500
0!
1)
1$
#137000
0$
#137500
1$
#138000
0$
#138100
0#
#138500
0<
1$
#139000
0$
#139500
12
0&
0=
1$
#140000
0$
#140500
0'
13
1$
#141000
0$
#141500
0)
1$
#142000
0$
#142500
1$
#143000
0$
#143100
1#
#143500
1<
1$
#144000
0$
#144500
02
1&
1=
1$
#145000
0$
#145500
1!
1'
03
1$
#146000
0$
#146500
0!
1)
1$
#147000
0$
#147500
1$
#148000
0$
#148100
0#
#148500
0<
1$
#149000
0$
#149500
12
0&
0=
1$
#150000
0$
#150500
0'
13
1$
#151000
0$
#151500
0)
1$
#152000
0$
#152500
1$
#153000
0$
#153100
1#
#153500
1<
1$
#154000
0$
#154500
02
1&
1=
1$
#155000
0$
#155500
1!
1'
03
1$
#156000
0$
#156500
0!
1)
1$
#157000
0$
#157500
1$
#158000
0$
#158100
0#
#158500
0<
1$
#159000
0$
#159500
12
0&
0=
1$
#160000
0$
#160500
0'
13
1$
#161000
0$
#161500
0)
1$
#162000
0$
#162500
1$
#163000
0$
#163100
1#
#163500
1<
1$
#164000
0$
#164500
02
1&
1=
1$
#165000
0$
#165500
1!
1'
03
1$
#166000
0$
#166500
0!
1)
1$
#167000
0$
#167500
1$
#168000
0$
#168100
0#
#168500
0<
1$
#169000
0$
#169500
12
0&
0=
1$
#170000
0$
#170500
0'
13
1$
#171000
0$
#171500
0)
1$
#172000
0$
#172500
1$
#173000
0$
#173100
1#
#173500
1<
1$
#174000
0$
#174500
02
1&
1=
1$
#175000
0$
#175500
1!
1'
03
1$
#176000
0$
#176500
0!
1)
1$
#177000
0$
#177500
1$
#178000
0$
#178100
0#
#178500
0<
1$
#179000
0$
#179500
12
0&
0=
1$
#180000
0$
#180500
0'
13
1$
#181000
0$
#181500
0)
1$
#182000
0$
#182500
1$
#183000
0$
#183100
1#
#183500
1<
1$
#184000
0$
#184500
02
1&
1=
1$
#185000
0$
#185500
1!
1'
03
1$
#186000
0$
#186500
0!
1)
1$
#187000
0$
#187500
1$
#188000
0$
#188100
0#
#188500
0<
1$
#189000
0$
#189500
12
0&
0=
1$
#190000
0$
#190500
0'
13
1$
#191000
0$
#191500
0)
1$
#192000
0$
#192500
1$
#193000
0$
#193100
1#
#193500
1<
1$
#194000
0$
#194500
02
1&
1=
1$
#195000
0$
#195500
1!
1'
03
1$
#196000
0$
#196500
0!
1)
1$
#197000
0$
#197500
1$
#198000
0$
#198100
0#
#198500
0<
1$
#199000
0$
#199500
12
0&
0=
1$
#200000
0$
#200500
0'
13
1$
#201000
0$
#201500
0)
1$
#202000
0$
#202500
1$
#203000
0$
#203100
1#
#203500
1<
1$
#204000
0$
#204500
02
1&
1=
1$
#205000
0$
#205500
1!
1'
03
1$
#206000
0$
#206500
0!
1)
1$
#207000
0$
#207500
1$
#208000
0$
#208100
0#
#208500
0<
1$
#209000
0$
#209500
12
0&
0=
1$
#210000
0$
#210500
0'
13
1$
#211000
0$
#211500
0)
1$
#212000
0$
#212500
1$
#213000
0$
#213100
1#
#213500
1<
1$
#214000
0$
#214500
02
1&
1=
1$
#215000
0$
#215500
1!
1'
03
1$
#216000
0$
#216500
0!
1)
1$
#217000
0$
#217500
1$
#218000
0$
#218100
0#
#218500
0<
1$
#219000
0$
#219500
12
0&
0=
1$
#220000
0$
#220500
0'
13
1$
#221000
0$
#221500
0)
1$
#222000
0$
#222500
1$
#223000
0$
#223100
1#
#223500
1<
1$
#224000
0$
#224500
02
1&
1=
1$
#225000
0$
#225500
1!
1'
03
1$
#226000
0$
#226500
0!
1)
1$
#227000
0$
#227500
1$
#228000
0$
#228100
0#
#228500
0<
1$
#229000
0$
#229500
12
0&
0=
1$
#230000
0$
#230500
0'
13
1$
#231000
0$
#231500
0)
1$
#232000
0$
#232500
1$
#233000
0$
#233100
1#
#233500
1<
1$
#234000
0$
#234500
02
1&
1=
1$
#235000
0$
#235500
1!
1'
03
1$
#236000
0$
#236500
0!
1)
1$
#237000
0$
#237500
1$
#238000
0$
#238100
0#
#238500
0<
1$
#239000
0$
#239500
12
0&
0=
1$
#240000
0$
#240500
0'
13
1$
#241000
0$
#241500
0)
1$
#242000
0$
#242500
1$
#243000
0$
#243100
1#
#243500
1<
1$
#244000
0$
#244500
02
1&
1=
1$
#245000
0$
#245500
1!
1'
03
1$
#246000
0$
#246500
0!
1)
1$
#247000
0$
#247500
1$
#248000
0$
#248100
0#
#248500
0<
1$
#249000
0$
#249500
12
0&
0=
1$
#250000
0$
#250500
0'
13
1$
#251000
0$
#251500
0)
1$
#252000
0$
#252500
1$
#253000
0$
#253100
1#
#253500
1<
1$
#254000
0$
#254500
02
1&
1=
1$
#255000
0$
#255500
1!
1'
03
1$
#256000
0$
#256500
0!
1)
1$
#257000
0$
#257500
1$
#258000
0$
#258100
0#
#258500
0<
1$
#259000
0$
#259500
12
0&
0=
1$
#260000
0$
#260500
0'
13
1$
#261000
0$
#261500
0)
1$
#262000
0$
#262500
1$
#263000
0$
#263100
1#
#263500
1<
1$
#264000
0$
#264500
02
1&
1=
1$
#265000
0$
#265500
1!
1'
03
1$
#266000
0$
#266500
0!
1)
1$
#267000
0$
#267500
1$
#268000
0$
#268100
0#
#268500
0<
1$
#269000
0$
#269500
12
0&
0=
1$
#270000
0$
#270500
0'
13
1$
#271000
0$
#271500
0)
1$
#272000
0$
#272500
1$
#273000
0$
#273100
1#
#273500
1<
1$
#274000
0$
#274500
02
1&
1=
1$
#275000
0$
#275500
1!
1'
03
1$
#276000
0$
#276500
0!
1)
1$
#277000
0$
#277500
1$
#278000
0$
#278100
0#
#278500
0<
1$
#279000
0$
#279500
12
0&
0=
1$
#280000
0$
#280500
0'
13
1$
#281000
0$
#281500
0)
1$
#282000
0$
#282500
1$
#283000
0$
#283100
1#
#283500
1<
1$
#284000
0$
#284500
02
1&
1=
1$
#285000
0$
#285500
1!
1'
03
1$
#286000
0$
#286500
0!
1)
1$
#287000
0$
#287500
1$
#288000
0$
#288100
0#
#288500
0<
1$
#289000
0$
#289500
12
0&
0=
1$
#290000
0$
#290500
0'
13
1$
#291000
0$
#291500
0)
1$
#292000
0$
#292500
1$
#293000
0$
#293100
1#
#293500
1<
1$
#294000
0$
#294500
02
1&
1=
1$
#295000
0$
#295500
1!
1'
03
1$
#296000
0$
#296500
0!
1)
1$
#297000
0$
#297500
1$
#298000
0$
#298100
0#
#298500
0<
1$
#299000
0$
#299500
12
0&
0=
1$
#300000
0$
#300500
0'
13
1$
#301000
0$
#301500
0)
1$
#302000
0$
#302500
1$
#303000
0$
#303100
1#
#303500
1<
1$
#304000
0$
#304500
02
1&
1=
1$
#305000
0$
#305500
1!
1'
03
1$
#306000
0$
#306500
0!
1)
1$
#307000
0$
#307500
1$
#308000
0$
#308100
0#
#308500
0<
1$
#309000
0$
#309500
12
0&
0=
1$
#310000
0$
#310500
0'
13
1$
#311000
0$
#311500
0)
1$
#312000
0$
#312500
1$
#313000
0$
#313100
1#
#313500
1<
1$
#314000
0$
#314500
02
1&
1=
1$
#315000
0$
#315500
1!
1'
03
1$
#316000
0$
#316500
0!
1)
1$
#317000
0$
#317500
1$
#318000
0$
#318100
0#
#318500
0<
1$
#319000
0$
#319500
12
0&
0=
1$
#320000
0$
#320500
0'
13
1$
#321000
0$
#321500
0)
1$
#322000
0$
#322500
1$
#323000
0$
#323100
1#
#323500
1<
1$
#324000
0$
#324500
02
1&
1=
1$
#325000
0$
#325500
1!
1'
03
1$
#326000
0$
#326500
0!
1)
1$
#327000
0$
#327500
1$
#328000
0$
#328100
0#
#328500
0<
1$
#329000
0$
#329500
12
0&
0=
1$
#330000
0$
#330500
0'
13
1$
#331000
0$
#331500
0)
1$
#332000
0$
#332500
1$
#333000
0$
#333100
1#
#333500
1<
1$
#334000
0$
#334500
02
1&
1=
1$
#335000
0$
#335500
1!
1'
03
1$
#336000
0$
#336500
0!
1)
1$
#337000
0$
#337500
1$
#338000
0$
#338100
0#
#338500
0<
1$
#339000
0$
#339500
12
0&
0=
1$
#340000
0$
#340500
0'
13
1$
#341000
0$
#341500
0)
1$
#342000
0$
#342500
1$
#343000
0$
#343100
1#
#343500
1<
1$
#344000
0$
#344500
02
1&
1=
1$
#345000
0$
#345500
1!
1'
03
1$
#346000
0$
#346500
0!
1)
1$
#347000
0$
#347500
1$
#348000
0$
#348100
0#
#348500
0<
1$
#349000
0$
#349500
12
0&
0=
1$
#350000
0$
#350500
0'
13
1$
#351000
0$
#351500
0)
1$
#352000
0$
#352500
1$
#353000
0$
#353100
1#
#353500
1<
1$
#354000
0$
#354500
02
1&
1=
1$
#355000
0$
#355500
1!
1'
03
1$
#356000
0$
#356500
0!
1)
1$
