专业基础/数字系统设计实验/实验完整代码lab1-3-5-11-15-19/lab11_button_process_unit/src/code/debouncer/counter.v
module counter #(
    parameter n, //mod number
    parameter counter_bits  //number of bits needed to count to n
)(
    input clk,
    input reset,
    input en,
    output reg [counter_bits-1:0] q,
    output co
);
    assign co = (q == n-1) && en; //carry generates when q equals to n-1 and en signal is true
    always @(posedge clk) begin
        if (reset) q <= 0; //if reset is true, then reset q to 0
        else if (en) begin
            if (q == n-1) q <= 0; //if q equals to n-1, then reset q to 0
            else q <= q + 1;
        end
    end
endmodule

专业基础/数字系统设计实验/实验完整代码lab1-3-5-11-15-19/lab11_button_process_unit/src/testbench/debouncer/counter_tb.v
`timescale 1ns / 1ps

module counter_tb();

    // 参数配置
    localparam MOD_N = 10;           // 模10计数器
    localparam COUNTER_BITS = 4;     // 需要4位二进制表示0-9
    
    // 信号定义
    reg clk;
    reg reset;
    reg en;
    wire [COUNTER_BITS-1:0] q;
    wire co;
    
    // 实例化计数器
    counter #(
        .n(MOD_N),
        .counter_bits(COUNTER_BITS)
    ) u_counter (
        .clk(clk),
        .reset(reset),
        .en(en),
        .q(q),
        .co(co)
    );
    
    // 时钟生成：周期20ns (50MHz)
    always begin
        clk = 0;
        #10;
        clk = 1;
        #10;
    end
    
    // 测试激励
    initial begin
        // 初始化
        reset = 1;
        en = 0;
        
        // 释放复位
        #30;
        reset = 0;
        #10;
        
        // 测试1：使能计数器
        $display("\n=== Test 1: Normal counting ===");
        en = 1;
        
        // 等待计数到9并产生进位
        #400;  // 计数10个周期 (0->9)
        
        // 测试2：计数过程中复位
        $display("\n=== Test 2: Reset during counting ===");
        #20;
        reset = 1;
        #30;
        reset = 0;
        
        // 继续计数
        #200;
        
        // 测试3：禁用使能
        $display("\n=== Test 3: Disable enable signal ===");
        en = 0;
        #100;
        
        // 测试4：重新使能
        $display("\n=== Test 4: Re-enable counting ===");
        en = 1;
        #200;
        
        // 测试5：测试不同的模数（需要重新实例化或修改参数）
        $display("\n=== Test 5: Test completed ===");
        #50;
        
        $finish;
    end
    
    
    // 波形输出（可选）
    initial begin
        $dumpfile("prj/vcd/counter.vcd");
        $dumpvars(0, counter_tb);
    end
    
    // 断言：检查进位信号行为
    always @(posedge clk) begin
        // 当q等于n-1且en有效时，co应该为1
        if (q == MOD_N-1 && en && !reset)
            assert (co == 1) else
                $error("ERROR: co should be 1 when q=%d and en=1", q);
        
        // 其他情况co应该为0
        if ((q != MOD_N-1 || !en) && !reset)
            assert (co == 0) else
                $error("ERROR: co should be 0 when q=%d and en=%b", q, en);
    end
    
endmodule

专业基础/数字系统设计实验/实验完整代码lab1-3-5-11-15-19/lab11_button_process_unit/prj/vcd/counter.vcd
$date
	Mon Apr 13 19:43:03 2026
$end
$version
	Icarus Verilog
$end
$timescale
	1ps
$end
$scope module counter_tb $end
$var wire 4 ! q [3:0] $end
$var wire 1 " co $end
$var parameter 32 # COUNTER_BITS $end
$var parameter 32 $ MOD_N $end
$var reg 1 % clk $end
$var reg 1 & en $end
$var reg 1 ' reset $end
$scope module u_counter $end
$var wire 1 % clk $end
$var wire 1 " co $end
$var wire 1 & en $end
$var wire 1 ' reset $end
$var parameter 32 ( counter_bits $end
$var parameter 32 ) n $end
$var reg 4 * q [3:0] $end
$upscope $end
$upscope $end
$enddefinitions $end
$comment Show the parameter values. $end
$dumpall
b1010 )
b100 (
b1010 $
b100 #
$end
#0
$dumpvars
bx *
1'
0&
0%
0"
bx !
$end
#10000
b0 !
b0 *
1%
#20000
0%
#30000
1%
0'
#40000
0%
1&
#50000
b1 !
b1 *
1%
#60000
0%
#70000
b10 !
b10 *
1%
#80000
0%
#90000
b11 !
b11 *
1%
#100000
0%
#110000
b100 !
b100 *
1%
#120000
0%
#130000
b101 !
b101 *
1%
#140000
0%
#150000
b110 !
b110 *
1%
#160000
0%
#170000
b111 !
b111 *
1%
#180000
0%
#190000
b1000 !
b1000 *
1%
#200000
0%
#210000
1"
b1001 !
b1001 *
1%
#220000
0%
#230000
0"
b0 !
b0 *
1%
#240000
0%
#250000
b1 !
b1 *
1%
#260000
0%
#270000
b10 !
b10 *
1%
#280000
0%
#290000
b11 !
b11 *
1%
#300000
0%
#310000
b100 !
b100 *
1%
#320000
0%
#330000
b101 !
b101 *
1%
#340000
0%
#350000
b110 !
b110 *
1%
#360000
0%
#370000
b111 !
b111 *
1%
#380000
0%
#390000
b1000 !
b1000 *
1%
#400000
0%
#410000
1"
b1001 !
b1001 *
1%
#420000
0%
#430000
0"
b0 !
b0 *
1%
#440000
0%
#450000
b1 !
b1 *
1%
#460000
0%
1'
#470000
b0 !
b0 *
1%
#480000
0%
#490000
b1 !
b1 *
1%
0'
#500000
0%
#510000
b10 !
b10 *
1%
#520000
0%
#530000
b11 !
b11 *
1%
#540000
0%
#550000
b100 !
b100 *
1%
#560000
0%
#570000
b101 !
b101 *
1%
#580000
0%
#590000
b110 !
b110 *
1%
#600000
0%
#610000
b111 !
b111 *
1%
#620000
0%
#630000
b1000 !
b1000 *
1%
#640000
0%
#650000
1"
b1001 !
b1001 *
1%
#660000
0%
#670000
0"
b0 !
b0 *
1%
#680000
0%
#690000
1%
0&
#700000
0%
#710000
1%
#720000
0%
#730000
1%
#740000
0%
#750000
1%
#760000
0%
#770000
1%
#780000
0%
#790000
b1 !
b1 *
1%
1&
#800000
0%
#810000
b10 !
b10 *
1%
#820000
0%
#830000
b11 !
b11 *
1%
#840000
0%
#850000
b100 !
b100 *
1%
#860000
0%
#870000
b101 !
b101 *
1%
#880000
0%
#890000
b110 !
b110 *
1%
#900000
0%
#910000
b111 !
b111 *
1%
#920000
0%
#930000
b1000 !
b1000 *
1%
#940000
0%
#950000
1"
b1001 !
b1001 *
1%
#960000
0%
#970000
0"
b0 !
b0 *
1%
#980000
0%
#990000
b1 !
b1 *
1%
#1000000
0%
#1010000
b10 !
b10 *
1%
#1020000
0%
#1030000
b11 !
b11 *
1%
